{
  "faq": {
    "title": "Bieži uzdotie jautājumi",
    "description": "Atbildes uz visbiežāk uzdotajiem jautājumiem.",
    "faq_1": {
      "question": "Vai GroupDocs.Merger bibliotēkai ir nepieciešama cita trešās puses programmatūra, lai manipulētu ar dokumentiem?",
      "answer": "GroupDocs.Merger neprasa instalēt ārēju programmatūru, piemēram, Adobe Acrobat, Microsoft Office vai jebkuru citu."
    },
    "faq_2": {
      "question": "Vai es varu izmēģināt GroupDocs.Merger bibliotēku pirms tās iegādes?",
      "answer": "Jā, varat izmēģināt GroupDocs.Merger, nepērkot licenci. Kad bibliotēka ir instalēta bez licences, tā darbojas izmēģinājuma režīmā. Šajā režīmā iegūtajam dokumentam tiek pievienotas izmēģinājuma emblēmas, un tas tiek apgriezts līdz pirmajām 3 lapām. Ja vēlaties pārbaudīt GroupDocs.Merger bez izmēģinājuma versijas ierobežojumiem, varat arī pieprasīt 30 dienu pagaidu licenci. Plašāku informāciju skatiet sadaļā [Iegūt pagaidu licenci](https://purchase.groupdocs.com/temporary-license/)."
    },
    "faq_3": {
      "question": "Kādas licences jums ir?",
      "answer": "Mēs piedāvājam vairākus licenču veidus, lai tie atbilstu konkrētu izstrādātāju vai uzņēmumu vajadzībām. Licenču veidi ir atkarīgi no izstrādātāju skaita, izstrādātāju vietņu atrašanās vietu skaita un tā, vai jums ir jāpiegādā mūsu SDK/API gala klientiem. Varat arī izvēlēties mērītās licences, pamatojoties uz produkta ikmēneša lietojumu. Uzziniet vairāk vietnē [licenču veidi](https://purchase.groupdocs.com/policies/license-types/)."
    }
  }
}