{
  "overview": {
    "title": "የቡድን ሰነዶች. ውህደት በጨረፍታ",
    "description": "በጃቫ አፕሊኬሽኖች ውስጥ ሰነዶችን፣ ስላይዶችን እና ንድፎችን ለማጣመር፣ ለመከፋፈል፣ ለመለዋወጥ፣ ለመከርከም ወይም ለማስወገድ API",
    "feature_1": {
      "title": "በጃቫ ውስጥ ብዙ ሰነዶችን ያለምንም ጥረት ያዋህዱ",
      "description": "በቀላሉ የፒዲኤፍ እና የቢሮ ፋይሎችን በጃቫ ውስጥ ወደ አንድ ሰነድ ያዋህዱ፣ የGroupDocs.Merger ቤተመፃህፍትን አቅም በመጠቀም። የተለያዩ የፋይል ዓይነቶችን ያለችግር እንዲያጣምሩ የሚያስችልዎ ሰፊ የቅርጸት ድጋፍ ተጠቃሚ ይሁኑ ይህም ምቹ እና የተሳለጠ ውህደት ሂደት ያስገኛል ።"
    },
    "feature_2": {
      "title": "ግዙፍ ፋይሎችን በቀላሉ በመከፋፈል የሰነድ አስተዳደርን ያመቻቹ",
      "description": "ትላልቅ ፒዲኤፍ ወይም የቢሮ ፋይሎችን ወደ ትናንሽ፣ በቀላሉ ወደ ሚያዙ ክፍሎች ይከፋፍሏቸው። ሰነዶችን በተወሰኑ ገፆች፣ ክልሎች ላይ ተመስርተው መከፋፈል ወይም የግለሰብ ገጾችን በቀላል እና በምቾት ማውጣት ይችላሉ። የ GroupDocs.Merger ቤተ-መጽሐፍት እንከን የለሽ ችሎታዎችን በመጠቀም የሰነድ አስተዳደርዎን ያቀላቅሉ እና ፋይሎችዎን ይበልጥ የተደራጁ እና የሚተዳደሩ ያድርጓቸው።"
    },
    "feature_3": {
      "title": "የሰነድ መዋቅርዎን ያብጁ እና በፋይሎችዎ ላይ ሙሉ ቁጥጥር ያድርጉ",
      "description": "ገጾችን እንደገና በማዘዝ፣ በመለዋወጥ ወይም በማስወገድ በቀላሉ ይቆጣጠሩ። ለግል የተበጀ የፋይል መዋቅር ለመፍጠር በተለዋዋጭነት ሰነዶችዎን በልዩ መስፈርቶችዎ መሠረት ያደራጁ እና ያብጁ።"
    }
  }
}