{
  "head": {
    "title": "Node.js ドキュメントマージング API | PDF、Word、Excel のマージ",
    "description": "ドキュメントをマージするための Node.js API。PDF、Microsoft Word、Excel、PowerPoint、Visio、XPS、および EPUB ファイルからページをマージ、分割、スワップ、順序変更、削除します。"
  },
  "header": {
    "title_1": "ドキュメントをマージ",
    "title_2": "Node.js API を使用して",
    "description": "PDF と Office ドキュメントを結合、分割、編集するための柔軟な API です。",
    "words": {
      "for": "用"
    }
  },
  "actions": {
    "main": "NPM の無料ダウンロード",
    "alt": "ライセンス取得",
    "title": "始める準備はできましたか？",
    "description": "GroupDocs.Merger を無料で試すか、ライセンスをリクエストしてください"
  },
  "release": {
    "title": "バージョン {0} リリース",
    "notes": "最新の更新情報をチェックしてください",
    "downloads": "ダウンロード"
  }
}